{
    "2000-01-01": "New Year's Day",
    "2000-01-03": "New Year's Day (observed)",
    "2000-03-13": "Commonwealth Day",
    "2000-04-21": "Good Friday",
    "2000-04-24": "Easter Monday",
    "2000-05-01": "May Day",
    "2000-05-29": "Spring Bank Holiday",
    "2000-06-19": "Queen's Birthday",
    "2000-08-28": "Late Summer Bank Holiday",
    "2000-09-10": "Gibraltar National Day",
    "2000-09-11": "Gibraltar National Day (observed)",
    "2000-12-25": "Christmas Day",
    "2000-12-26": "Boxing Day",
    "2001-01-01": "New Year's Day",
    "2001-03-12": "Commonwealth Day",
    "2001-04-13": "Good Friday",
    "2001-04-16": "Easter Monday",
    "2001-05-01": "May Day",
    "2001-05-28": "Spring Bank Holiday",
    "2001-06-18": "Queen's Birthday",
    "2001-08-27": "Late Summer Bank Holiday",
    "2001-09-10": "Gibraltar National Day",
    "2001-12-25": "Christmas Day",
    "2001-12-26": "Boxing Day",
    "2002-01-01": "New Year's Day",
    "2002-03-11": "Commonwealth Day",
    "2002-03-29": "Good Friday",
    "2002-04-01": "Easter Monday",
    "2002-05-01": "May Day",
    "2002-05-27": "Spring Bank Holiday",
    "2002-06-10": "Queen's Birthday",
    "2002-08-26": "Summer Bank Holiday",
    "2002-09-10": "Gibraltar National Day",
    "2002-12-25": "Christmas Day",
    "2002-12-26": "Boxing Day",
    "2003-01-01": "New Year's Day",
    "2003-03-10": "Commonwealth Day",
    "2003-04-18": "Good Friday",
    "2003-04-21": "Easter Monday",
    "2003-05-01": "May Day",
    "2003-05-26": "Spring Bank Holiday",
    "2003-06-16": "Queen's Birthday",
    "2003-08-25": "Summer Bank Holiday",
    "2003-09-10": "Gibraltar National Day",
    "2003-12-25": "Christmas Day",
    "2003-12-26": "Boxing Day",
    "2004-01-01": "New Year's Day",
    "2004-03-08": "Commonwealth Day",
    "2004-04-09": "Good Friday",
    "2004-04-12": "Easter Monday",
    "2004-05-01": "May Day",
    "2004-05-03": "May Day (observed)",
    "2004-05-31": "Spring Bank Holiday",
    "2004-06-14": "Queen's Birthday",
    "2004-08-04": "Tercentenary Holiday",
    "2004-08-30": "Summer Bank Holiday",
    "2004-09-10": "Gibraltar National Day",
    "2004-12-25": "Christmas Day",
    "2004-12-26": "Boxing Day",
    "2004-12-27": "Christmas Day (observed)",
    "2004-12-28": "Boxing Day (observed)",
    "2005-01-01": "New Year's Day",
    "2005-01-03": "New Year's Day (observed)",
    "2005-03-14": "Commonwealth Day",
    "2005-03-25": "Good Friday",
    "2005-03-28": "Easter Monday",
    "2005-05-01": "May Day",
    "2005-05-02": "May Day (observed)",
    "2005-05-30": "Spring Bank Holiday",
    "2005-06-13": "Queen's Birthday",
    "2005-08-29": "Summer Bank Holiday",
    "2005-09-10": "Gibraltar National Day",
    "2005-09-12": "Gibraltar National Day (observed)",
    "2005-12-25": "Christmas Day",
    "2005-12-26": "Boxing Day",
    "2005-12-27": "Christmas Day (observed)",
    "2006-01-01": "New Year's Day",
    "2006-01-02": "New Year's Day (observed)",
    "2006-03-13": "Commonwealth Day",
    "2006-04-14": "Good Friday",
    "2006-04-17": "Easter Monday",
    "2006-05-01": "May Day",
    "2006-05-29": "Spring Bank Holiday",
    "2006-06-19": "Queen's Birthday",
    "2006-08-28": "Summer Bank Holiday",
    "2006-09-10": "Gibraltar National Day",
    "2006-09-11": "Gibraltar National Day (observed)",
    "2006-12-25": "Christmas Day",
    "2006-12-26": "Boxing Day",
    "2007-01-01": "New Year's Day",
    "2007-03-12": "Commonwealth Day",
    "2007-04-06": "Good Friday",
    "2007-04-09": "Easter Monday",
    "2007-05-07": "May Day",
    "2007-05-28": "Spring Bank Holiday",
    "2007-06-18": "Queen's Birthday",
    "2007-08-27": "Summer Bank Holiday",
    "2007-09-10": "Gibraltar National Day",
    "2007-12-25": "Christmas Day",
    "2007-12-26": "Boxing Day",
    "2008-01-01": "New Year's Day",
    "2008-03-10": "Commonwealth Day",
    "2008-03-21": "Good Friday",
    "2008-03-24": "Easter Monday",
    "2008-05-05": "May Day",
    "2008-05-26": "Spring Bank Holiday",
    "2008-06-16": "Queen's Birthday",
    "2008-08-25": "Late Summer Bank Holiday",
    "2008-09-10": "Gibraltar National Day",
    "2008-12-25": "Christmas Day",
    "2008-12-26": "Boxing Day",
    "2009-01-01": "New Year's Day",
    "2009-01-12": "Bank Holiday",
    "2009-03-09": "Commonwealth Day",
    "2009-04-10": "Good Friday",
    "2009-04-13": "Easter Monday",
    "2009-05-04": "May Day",
    "2009-05-25": "Spring Bank Holiday",
    "2009-06-15": "Queen's Birthday",
    "2009-08-31": "Late Summer Bank Holiday",
    "2009-09-10": "Gibraltar National Day",
    "2009-12-25": "Christmas Day",
    "2009-12-26": "Boxing Day",
    "2009-12-28": "Boxing Day (observed)",
    "2010-01-01": "New Year's Day",
    "2010-03-08": "Commonwealth Day",
    "2010-04-02": "Good Friday",
    "2010-04-05": "Easter Monday",
    "2010-05-01": "May Day",
    "2010-05-03": "May Day (observed)",
    "2010-05-31": "Spring Bank Holiday",
    "2010-06-14": "Queen's Birthday",
    "2010-08-30": "Late Summer Bank Holiday",
    "2010-09-10": "Gibraltar National Day",
    "2010-12-25": "Christmas Day",
    "2010-12-26": "Boxing Day",
    "2010-12-27": "Christmas Day (observed)",
    "2010-12-28": "Boxing Day (observed)",
    "2011-01-01": "New Year's Day",
    "2011-01-03": "New Year's Day (observed)",
    "2011-03-14": "Commonwealth Day",
    "2011-04-22": "Good Friday",
    "2011-04-25": "Easter Monday",
    "2011-05-01": "May Day",
    "2011-05-02": "May Day (observed)",
    "2011-05-30": "Spring Bank Holiday",
    "2011-06-13": "Queen's Birthday",
    "2011-08-29": "Late Summer Bank Holiday",
    "2011-09-10": "Gibraltar National Day",
    "2011-09-12": "Gibraltar National Day (observed)",
    "2011-12-25": "Christmas Day",
    "2011-12-26": "Boxing Day",
    "2011-12-27": "Christmas Day (observed)",
    "2012-01-01": "New Year's Day",
    "2012-01-02": "New Year's Day (observed)",
    "2012-03-12": "Commonwealth Day",
    "2012-04-06": "Good Friday",
    "2012-04-09": "Easter Monday",
    "2012-05-01": "May Day",
    "2012-06-04": "Spring Bank Holiday",
    "2012-06-05": "Queen's Diamond Jubilee",
    "2012-06-18": "Queen's Birthday",
    "2012-08-27": "Late Summer Bank Holiday",
    "2012-09-10": "Gibraltar National Day",
    "2012-12-25": "Christmas Day",
    "2012-12-26": "Boxing Day",
    "2013-01-01": "New Year's Day",
    "2013-03-11": "Commonwealth Day",
    "2013-03-29": "Good Friday",
    "2013-04-01": "Easter Monday",
    "2013-04-26": "Workers' Memorial Day",
    "2013-05-01": "May Day",
    "2013-05-27": "Spring Bank Holiday",
    "2013-06-17": "Queen's Birthday",
    "2013-08-26": "Late Summer Bank Holiday",
    "2013-09-10": "Gibraltar National Day",
    "2013-12-25": "Christmas Day",
    "2013-12-26": "Boxing Day",
    "2014-01-01": "New Year's Day",
    "2014-03-10": "Commonwealth Day",
    "2014-04-18": "Good Friday",
    "2014-04-21": "Easter Monday",
    "2014-04-28": "Workers' Memorial Day",
    "2014-05-01": "May Day",
    "2014-05-26": "Spring Bank Holiday",
    "2014-06-16": "Queen's Birthday",
    "2014-08-25": "Late Summer Bank Holiday",
    "2014-09-10": "Gibraltar National Day",
    "2014-12-25": "Christmas Day",
    "2014-12-26": "Boxing Day",
    "2015-01-01": "New Year's Day",
    "2015-03-09": "Commonwealth Day",
    "2015-04-03": "Good Friday",
    "2015-04-06": "Easter Monday",
    "2015-04-27": "Workers' Memorial Day",
    "2015-05-01": "May Day",
    "2015-05-25": "Spring Bank Holiday",
    "2015-06-15": "Queen's Birthday",
    "2015-08-31": "Late Summer Bank Holiday",
    "2015-09-07": "Evacuation Commemoration Day",
    "2015-09-10": "Gibraltar National Day",
    "2015-12-25": "Christmas Day",
    "2015-12-26": "Boxing Day",
    "2015-12-28": "Boxing Day (observed)",
    "2016-01-01": "New Year's Day",
    "2016-03-14": "Commonwealth Day",
    "2016-03-25": "Good Friday",
    "2016-03-28": "Easter Monday",
    "2016-04-28": "Workers' Memorial Day",
    "2016-05-01": "May Day",
    "2016-05-02": "May Day (observed)",
    "2016-05-30": "Spring Bank Holiday",
    "2016-06-13": "Queen's Birthday",
    "2016-08-29": "Late Summer Bank Holiday",
    "2016-09-05": "Gibraltar National Day",
    "2016-12-25": "Christmas Day",
    "2016-12-26": "Boxing Day",
    "2016-12-27": "Christmas Day (observed)",
    "2017-01-01": "New Year's Day",
    "2017-01-02": "New Year's Day (observed)",
    "2017-03-13": "Commonwealth Day",
    "2017-04-14": "Good Friday",
    "2017-04-17": "Easter Monday",
    "2017-04-28": "Workers' Memorial Day",
    "2017-05-01": "May Day",
    "2017-05-29": "Spring Bank Holiday",
    "2017-06-19": "Queen's Birthday",
    "2017-08-28": "Late Summer Bank Holiday",
    "2017-09-04": "Gibraltar National Day",
    "2017-12-25": "Christmas Day",
    "2017-12-26": "Boxing Day",
    "2018-01-01": "New Year's Day",
    "2018-03-12": "Commonwealth Day",
    "2018-03-30": "Good Friday",
    "2018-04-02": "Easter Monday",
    "2018-04-28": "Workers' Memorial Day",
    "2018-04-30": "Workers' Memorial Day (observed)",
    "2018-05-01": "May Day",
    "2018-05-28": "Spring Bank Holiday",
    "2018-06-11": "Queen's Birthday",
    "2018-08-27": "Late Summer Bank Holiday",
    "2018-09-10": "Gibraltar National Day",
    "2018-12-25": "Christmas Day",
    "2018-12-26": "Boxing Day",
    "2019-01-01": "New Year's Day",
    "2019-03-11": "Commonwealth Day",
    "2019-04-19": "Good Friday",
    "2019-04-22": "Easter Monday",
    "2019-04-28": "Workers' Memorial Day",
    "2019-04-29": "Workers' Memorial Day (observed)",
    "2019-05-01": "May Day",
    "2019-05-27": "Spring Bank Holiday",
    "2019-06-17": "Queen's Birthday",
    "2019-08-26": "Late Summer Bank Holiday",
    "2019-09-10": "Gibraltar National Day",
    "2019-12-25": "Christmas Day",
    "2019-12-26": "Boxing Day",
    "2020-01-01": "New Year's Day",
    "2020-03-09": "Commonwealth Day",
    "2020-04-10": "Good Friday",
    "2020-04-13": "Easter Monday",
    "2020-04-28": "Workers' Memorial Day",
    "2020-05-01": "May Day",
    "2020-05-08": "75th Anniversary of VE Day",
    "2020-05-25": "Spring Bank Holiday",
    "2020-06-15": "Queen's Birthday",
    "2020-08-31": "Late Summer Bank Holiday",
    "2020-09-10": "Gibraltar National Day",
    "2020-12-25": "Christmas Day",
    "2020-12-26": "Boxing Day",
    "2020-12-28": "Boxing Day (observed)",
    "2021-01-01": "New Year's Day",
    "2021-02-15": "Commonwealth Day",
    "2021-04-02": "Good Friday",
    "2021-04-05": "Easter Monday",
    "2021-04-28": "Workers' Memorial Day",
    "2021-05-01": "May Day",
    "2021-05-03": "May Day (observed)",
    "2021-05-31": "Spring Bank Holiday",
    "2021-06-14": "Queen's Birthday",
    "2021-08-30": "Late Summer Bank Holiday",
    "2021-09-10": "Gibraltar National Day",
    "2021-12-25": "Christmas Day",
    "2021-12-26": "Boxing Day",
    "2021-12-27": "Christmas Day (observed)",
    "2021-12-28": "Boxing Day (observed)",
    "2022-01-01": "New Year's Day",
    "2022-01-03": "New Year's Day (observed)",
    "2022-02-21": "Commonwealth Day",
    "2022-04-15": "Good Friday",
    "2022-04-18": "Easter Monday",
    "2022-04-28": "Workers' Memorial Day",
    "2022-05-01": "May Day",
    "2022-05-02": "May Day (observed)",
    "2022-06-02": "Spring Bank Holiday",
    "2022-06-03": "Queen's Platinum Jubilee",
    "2022-06-13": "Queen's Birthday",
    "2022-08-29": "Late Summer Bank Holiday",
    "2022-09-10": "Gibraltar National Day",
    "2022-09-12": "Gibraltar National Day (observed)",
    "2022-12-25": "Christmas Day",
    "2022-12-26": "Boxing Day",
    "2022-12-27": "Christmas Day (observed)",
    "2023-01-01": "New Year's Day",
    "2023-01-02": "New Year's Day (observed)",
    "2023-02-20": "Winter Midterm Bank Holiday",
    "2023-04-07": "Good Friday",
    "2023-04-10": "Easter Monday",
    "2023-04-28": "Workers' Memorial Day",
    "2023-05-01": "May Day",
    "2023-05-08": "Special King's Coronation Bank Holiday",
    "2023-05-29": "Spring Bank Holiday",
    "2023-06-19": "King's Birthday",
    "2023-08-28": "Late Summer Bank Holiday",
    "2023-09-10": "Gibraltar National Day",
    "2023-09-11": "Gibraltar National Day (observed)",
    "2023-12-25": "Christmas Day",
    "2023-12-26": "Boxing Day",
    "2024-01-01": "New Year's Day",
    "2024-02-12": "Winter Midterm Bank Holiday",
    "2024-03-29": "Good Friday",
    "2024-04-01": "Easter Monday",
    "2024-04-28": "Workers' Memorial Day",
    "2024-04-29": "Workers' Memorial Day (observed)",
    "2024-05-01": "May Day",
    "2024-05-27": "Spring Bank Holiday",
    "2024-06-17": "King's Birthday",
    "2024-08-26": "Late Summer Bank Holiday",
    "2024-09-10": "Gibraltar National Day",
    "2024-12-25": "Christmas Day",
    "2024-12-26": "Boxing Day",
    "2025-01-01": "New Year's Day",
    "2025-02-17": "Winter Midterm Bank Holiday",
    "2025-04-18": "Good Friday",
    "2025-04-21": "Easter Monday",
    "2025-04-28": "Workers' Memorial Day",
    "2025-05-01": "May Day",
    "2025-05-26": "Spring Bank Holiday",
    "2025-06-16": "King's Birthday",
    "2025-08-25": "Late Summer Bank Holiday",
    "2025-09-10": "Gibraltar National Day",
    "2025-12-25": "Christmas Day",
    "2025-12-26": "Boxing Day",
    "2026-01-01": "New Year's Day",
    "2026-02-16": "Winter Midterm Bank Holiday",
    "2026-04-03": "Good Friday",
    "2026-04-06": "Easter Monday",
    "2026-04-28": "Workers' Memorial Day",
    "2026-05-01": "May Day",
    "2026-05-25": "Spring Bank Holiday",
    "2026-06-15": "King's Birthday",
    "2026-08-31": "Late Summer Bank Holiday",
    "2026-09-10": "Gibraltar National Day",
    "2026-12-25": "Christmas Day",
    "2026-12-26": "Boxing Day",
    "2026-12-28": "Boxing Day (observed)",
    "2027-01-01": "New Year's Day",
    "2027-02-15": "Winter Midterm Bank Holiday",
    "2027-03-26": "Good Friday",
    "2027-03-29": "Easter Monday",
    "2027-04-28": "Workers' Memorial Day",
    "2027-05-01": "May Day",
    "2027-05-03": "May Day (observed)",
    "2027-05-31": "Spring Bank Holiday",
    "2027-06-14": "King's Birthday",
    "2027-08-30": "Late Summer Bank Holiday",
    "2027-09-10": "Gibraltar National Day",
    "2027-12-25": "Christmas Day",
    "2027-12-26": "Boxing Day",
    "2027-12-27": "Christmas Day (observed)",
    "2027-12-28": "Boxing Day (observed)",
    "2028-01-01": "New Year's Day",
    "2028-01-03": "New Year's Day (observed)",
    "2028-02-21": "Winter Midterm Bank Holiday",
    "2028-04-14": "Good Friday",
    "2028-04-17": "Easter Monday",
    "2028-04-28": "Workers' Memorial Day",
    "2028-05-01": "May Day",
    "2028-05-29": "Spring Bank Holiday",
    "2028-06-12": "King's Birthday",
    "2028-08-28": "Late Summer Bank Holiday",
    "2028-09-10": "Gibraltar National Day",
    "2028-09-11": "Gibraltar National Day (observed)",
    "2028-12-25": "Christmas Day",
    "2028-12-26": "Boxing Day",
    "2029-01-01": "New Year's Day",
    "2029-02-19": "Winter Midterm Bank Holiday",
    "2029-03-30": "Good Friday",
    "2029-04-02": "Easter Monday",
    "2029-04-28": "Workers' Memorial Day",
    "2029-04-30": "Workers' Memorial Day (observed)",
    "2029-05-01": "May Day",
    "2029-05-28": "Spring Bank Holiday",
    "2029-06-11": "King's Birthday",
    "2029-08-27": "Late Summer Bank Holiday",
    "2029-09-10": "Gibraltar National Day",
    "2029-12-25": "Christmas Day",
    "2029-12-26": "Boxing Day",
    "2030-01-01": "New Year's Day",
    "2030-02-18": "Winter Midterm Bank Holiday",
    "2030-04-19": "Good Friday",
    "2030-04-22": "Easter Monday",
    "2030-04-28": "Workers' Memorial Day",
    "2030-04-29": "Workers' Memorial Day (observed)",
    "2030-05-01": "May Day",
    "2030-05-27": "Spring Bank Holiday",
    "2030-06-10": "King's Birthday",
    "2030-08-26": "Late Summer Bank Holiday",
    "2030-09-10": "Gibraltar National Day",
    "2030-12-25": "Christmas Day",
    "2030-12-26": "Boxing Day",
    "2031-01-01": "New Year's Day",
    "2031-02-17": "Winter Midterm Bank Holiday",
    "2031-04-11": "Good Friday",
    "2031-04-14": "Easter Monday",
    "2031-04-28": "Workers' Memorial Day",
    "2031-05-01": "May Day",
    "2031-05-26": "Spring Bank Holiday",
    "2031-06-16": "King's Birthday",
    "2031-08-25": "Late Summer Bank Holiday",
    "2031-09-10": "Gibraltar National Day",
    "2031-12-25": "Christmas Day",
    "2031-12-26": "Boxing Day",
    "2032-01-01": "New Year's Day",
    "2032-02-16": "Winter Midterm Bank Holiday",
    "2032-03-26": "Good Friday",
    "2032-03-29": "Easter Monday",
    "2032-04-28": "Workers' Memorial Day",
    "2032-05-01": "May Day",
    "2032-05-03": "May Day (observed)",
    "2032-05-31": "Spring Bank Holiday",
    "2032-06-14": "King's Birthday",
    "2032-08-30": "Late Summer Bank Holiday",
    "2032-09-10": "Gibraltar National Day",
    "2032-12-25": "Christmas Day",
    "2032-12-26": "Boxing Day",
    "2032-12-27": "Christmas Day (observed)",
    "2032-12-28": "Boxing Day (observed)",
    "2033-01-01": "New Year's Day",
    "2033-01-03": "New Year's Day (observed)",
    "2033-02-21": "Winter Midterm Bank Holiday",
    "2033-04-15": "Good Friday",
    "2033-04-18": "Easter Monday",
    "2033-04-28": "Workers' Memorial Day",
    "2033-05-01": "May Day",
    "2033-05-02": "May Day (observed)",
    "2033-05-30": "Spring Bank Holiday",
    "2033-06-13": "King's Birthday",
    "2033-08-29": "Late Summer Bank Holiday",
    "2033-09-10": "Gibraltar National Day",
    "2033-09-12": "Gibraltar National Day (observed)",
    "2033-12-25": "Christmas Day",
    "2033-12-26": "Boxing Day",
    "2033-12-27": "Christmas Day (observed)",
    "2034-01-01": "New Year's Day",
    "2034-01-02": "New Year's Day (observed)",
    "2034-02-20": "Winter Midterm Bank Holiday",
    "2034-04-07": "Good Friday",
    "2034-04-10": "Easter Monday",
    "2034-04-28": "Workers' Memorial Day",
    "2034-05-01": "May Day",
    "2034-05-29": "Spring Bank Holiday",
    "2034-06-12": "King's Birthday",
    "2034-08-28": "Late Summer Bank Holiday",
    "2034-09-10": "Gibraltar National Day",
    "2034-09-11": "Gibraltar National Day (observed)",
    "2034-12-25": "Christmas Day",
    "2034-12-26": "Boxing Day",
    "2035-01-01": "New Year's Day",
    "2035-02-19": "Winter Midterm Bank Holiday",
    "2035-03-23": "Good Friday",
    "2035-03-26": "Easter Monday",
    "2035-04-28": "Workers' Memorial Day",
    "2035-04-30": "Workers' Memorial Day (observed)",
    "2035-05-01": "May Day",
    "2035-05-28": "Spring Bank Holiday",
    "2035-06-11": "King's Birthday",
    "2035-08-27": "Late Summer Bank Holiday",
    "2035-09-10": "Gibraltar National Day",
    "2035-12-25": "Christmas Day",
    "2035-12-26": "Boxing Day",
    "2036-01-01": "New Year's Day",
    "2036-02-18": "Winter Midterm Bank Holiday",
    "2036-04-11": "Good Friday",
    "2036-04-14": "Easter Monday",
    "2036-04-28": "Workers' Memorial Day",
    "2036-05-01": "May Day",
    "2036-05-26": "Spring Bank Holiday",
    "2036-06-16": "King's Birthday",
    "2036-08-25": "Late Summer Bank Holiday",
    "2036-09-10": "Gibraltar National Day",
    "2036-12-25": "Christmas Day",
    "2036-12-26": "Boxing Day",
    "2037-01-01": "New Year's Day",
    "2037-02-16": "Winter Midterm Bank Holiday",
    "2037-04-03": "Good Friday",
    "2037-04-06": "Easter Monday",
    "2037-04-28": "Workers' Memorial Day",
    "2037-05-01": "May Day",
    "2037-05-25": "Spring Bank Holiday",
    "2037-06-15": "King's Birthday",
    "2037-08-31": "Late Summer Bank Holiday",
    "2037-09-10": "Gibraltar National Day",
    "2037-12-25": "Christmas Day",
    "2037-12-26": "Boxing Day",
    "2037-12-28": "Boxing Day (observed)",
    "2038-01-01": "New Year's Day",
    "2038-02-15": "Winter Midterm Bank Holiday",
    "2038-04-23": "Good Friday",
    "2038-04-26": "Easter Monday",
    "2038-04-28": "Workers' Memorial Day",
    "2038-05-01": "May Day",
    "2038-05-03": "May Day (observed)",
    "2038-05-31": "Spring Bank Holiday",
    "2038-06-14": "King's Birthday",
    "2038-08-30": "Late Summer Bank Holiday",
    "2038-09-10": "Gibraltar National Day",
    "2038-12-25": "Christmas Day",
    "2038-12-26": "Boxing Day",
    "2038-12-27": "Christmas Day (observed)",
    "2038-12-28": "Boxing Day (observed)",
    "2039-01-01": "New Year's Day",
    "2039-01-03": "New Year's Day (observed)",
    "2039-02-21": "Winter Midterm Bank Holiday",
    "2039-04-08": "Good Friday",
    "2039-04-11": "Easter Monday",
    "2039-04-28": "Workers' Memorial Day",
    "2039-05-01": "May Day",
    "2039-05-02": "May Day (observed)",
    "2039-05-30": "Spring Bank Holiday",
    "2039-06-13": "King's Birthday",
    "2039-08-29": "Late Summer Bank Holiday",
    "2039-09-10": "Gibraltar National Day",
    "2039-09-12": "Gibraltar National Day (observed)",
    "2039-12-25": "Christmas Day",
    "2039-12-26": "Boxing Day",
    "2039-12-27": "Christmas Day (observed)",
    "2040-01-01": "New Year's Day",
    "2040-01-02": "New Year's Day (observed)",
    "2040-02-20": "Winter Midterm Bank Holiday",
    "2040-03-30": "Good Friday",
    "2040-04-02": "Easter Monday",
    "2040-04-28": "Workers' Memorial Day",
    "2040-04-30": "Workers' Memorial Day (observed)",
    "2040-05-01": "May Day",
    "2040-05-28": "Spring Bank Holiday",
    "2040-06-11": "King's Birthday",
    "2040-08-27": "Late Summer Bank Holiday",
    "2040-09-10": "Gibraltar National Day",
    "2040-12-25": "Christmas Day",
    "2040-12-26": "Boxing Day",
    "2041-01-01": "New Year's Day",
    "2041-02-18": "Winter Midterm Bank Holiday",
    "2041-04-19": "Good Friday",
    "2041-04-22": "Easter Monday",
    "2041-04-28": "Workers' Memorial Day",
    "2041-04-29": "Workers' Memorial Day (observed)",
    "2041-05-01": "May Day",
    "2041-05-27": "Spring Bank Holiday",
    "2041-06-10": "King's Birthday",
    "2041-08-26": "Late Summer Bank Holiday",
    "2041-09-10": "Gibraltar National Day",
    "2041-12-25": "Christmas Day",
    "2041-12-26": "Boxing Day",
    "2042-01-01": "New Year's Day",
    "2042-02-17": "Winter Midterm Bank Holiday",
    "2042-04-04": "Good Friday",
    "2042-04-07": "Easter Monday",
    "2042-04-28": "Workers' Memorial Day",
    "2042-05-01": "May Day",
    "2042-05-26": "Spring Bank Holiday",
    "2042-06-16": "King's Birthday",
    "2042-08-25": "Late Summer Bank Holiday",
    "2042-09-10": "Gibraltar National Day",
    "2042-12-25": "Christmas Day",
    "2042-12-26": "Boxing Day",
    "2043-01-01": "New Year's Day",
    "2043-02-16": "Winter Midterm Bank Holiday",
    "2043-03-27": "Good Friday",
    "2043-03-30": "Easter Monday",
    "2043-04-28": "Workers' Memorial Day",
    "2043-05-01": "May Day",
    "2043-05-25": "Spring Bank Holiday",
    "2043-06-15": "King's Birthday",
    "2043-08-31": "Late Summer Bank Holiday",
    "2043-09-10": "Gibraltar National Day",
    "2043-12-25": "Christmas Day",
    "2043-12-26": "Boxing Day",
    "2043-12-28": "Boxing Day (observed)",
    "2044-01-01": "New Year's Day",
    "2044-02-15": "Winter Midterm Bank Holiday",
    "2044-04-15": "Good Friday",
    "2044-04-18": "Easter Monday",
    "2044-04-28": "Workers' Memorial Day",
    "2044-05-01": "May Day",
    "2044-05-02": "May Day (observed)",
    "2044-05-30": "Spring Bank Holiday",
    "2044-06-13": "King's Birthday",
    "2044-08-29": "Late Summer Bank Holiday",
    "2044-09-10": "Gibraltar National Day",
    "2044-09-12": "Gibraltar National Day (observed)",
    "2044-12-25": "Christmas Day",
    "2044-12-26": "Boxing Day",
    "2044-12-27": "Christmas Day (observed)",
    "2045-01-01": "New Year's Day",
    "2045-01-02": "New Year's Day (observed)",
    "2045-02-20": "Winter Midterm Bank Holiday",
    "2045-04-07": "Good Friday",
    "2045-04-10": "Easter Monday",
    "2045-04-28": "Workers' Memorial Day",
    "2045-05-01": "May Day",
    "2045-05-29": "Spring Bank Holiday",
    "2045-06-12": "King's Birthday",
    "2045-08-28": "Late Summer Bank Holiday",
    "2045-09-10": "Gibraltar National Day",
    "2045-09-11": "Gibraltar National Day (observed)",
    "2045-12-25": "Christmas Day",
    "2045-12-26": "Boxing Day",
    "2046-01-01": "New Year's Day",
    "2046-02-19": "Winter Midterm Bank Holiday",
    "2046-03-23": "Good Friday",
    "2046-03-26": "Easter Monday",
    "2046-04-28": "Workers' Memorial Day",
    "2046-04-30": "Workers' Memorial Day (observed)",
    "2046-05-01": "May Day",
    "2046-05-28": "Spring Bank Holiday",
    "2046-06-11": "King's Birthday",
    "2046-08-27": "Late Summer Bank Holiday",
    "2046-09-10": "Gibraltar National Day",
    "2046-12-25": "Christmas Day",
    "2046-12-26": "Boxing Day",
    "2047-01-01": "New Year's Day",
    "2047-02-18": "Winter Midterm Bank Holiday",
    "2047-04-12": "Good Friday",
    "2047-04-15": "Easter Monday",
    "2047-04-28": "Workers' Memorial Day",
    "2047-04-29": "Workers' Memorial Day (observed)",
    "2047-05-01": "May Day",
    "2047-05-27": "Spring Bank Holiday",
    "2047-06-10": "King's Birthday",
    "2047-08-26": "Late Summer Bank Holiday",
    "2047-09-10": "Gibraltar National Day",
    "2047-12-25": "Christmas Day",
    "2047-12-26": "Boxing Day",
    "2048-01-01": "New Year's Day",
    "2048-02-17": "Winter Midterm Bank Holiday",
    "2048-04-03": "Good Friday",
    "2048-04-06": "Easter Monday",
    "2048-04-28": "Workers' Memorial Day",
    "2048-05-01": "May Day",
    "2048-05-25": "Spring Bank Holiday",
    "2048-06-15": "King's Birthday",
    "2048-08-31": "Late Summer Bank Holiday",
    "2048-09-10": "Gibraltar National Day",
    "2048-12-25": "Christmas Day",
    "2048-12-26": "Boxing Day",
    "2048-12-28": "Boxing Day (observed)",
    "2049-01-01": "New Year's Day",
    "2049-02-15": "Winter Midterm Bank Holiday",
    "2049-04-16": "Good Friday",
    "2049-04-19": "Easter Monday",
    "2049-04-28": "Workers' Memorial Day",
    "2049-05-01": "May Day",
    "2049-05-03": "May Day (observed)",
    "2049-05-31": "Spring Bank Holiday",
    "2049-06-14": "King's Birthday",
    "2049-08-30": "Late Summer Bank Holiday",
    "2049-09-10": "Gibraltar National Day",
    "2049-12-25": "Christmas Day",
    "2049-12-26": "Boxing Day",
    "2049-12-27": "Christmas Day (observed)",
    "2049-12-28": "Boxing Day (observed)",
    "2050-01-01": "New Year's Day",
    "2050-01-03": "New Year's Day (observed)",
    "2050-02-21": "Winter Midterm Bank Holiday",
    "2050-04-08": "Good Friday",
    "2050-04-11": "Easter Monday",
    "2050-04-28": "Workers' Memorial Day",
    "2050-05-01": "May Day",
    "2050-05-02": "May Day (observed)",
    "2050-05-30": "Spring Bank Holiday",
    "2050-06-13": "King's Birthday",
    "2050-08-29": "Late Summer Bank Holiday",
    "2050-09-10": "Gibraltar National Day",
    "2050-09-12": "Gibraltar National Day (observed)",
    "2050-12-25": "Christmas Day",
    "2050-12-26": "Boxing Day",
    "2050-12-27": "Christmas Day (observed)"
}
